.DS_Store
eclometer/__init__.py
eclometer/plots.py
eclometer/potentiostat.py
eclometer/interfaces/__init__.py
eclometer/interfaces/guiECL.py
eclometer/interfaces/runECL.py
eclometer/interfaces/utilCLI.py
potentiostat/.DS_Store
potentiostat/ECL.py
potentiostat/__init__.py
potentiostat/plots.py
potentiostat/potentiostat.py
potentiostat/utilSerial.py
eclometer-0.0.3.dist-info/LICENSE.txt
eclometer-0.0.3.dist-info/METADATA
eclometer-0.0.3.dist-info/WHEEL
eclometer-0.0.3.dist-info/top_level.txt
eclometer-0.0.3.dist-info/RECORD
